pytest_assert_utils/__init__.py
pytest_assert_utils/util/__init__.py
pytest_assert_utils/util/assertions.py
pytest_assert_utils/util/decl.py
pytest_assert_utils-0.3.0.dist-info/entry_points.txt
pytest_assert_utils-0.3.0.dist-info/LICENSE
pytest_assert_utils-0.3.0.dist-info/WHEEL
pytest_assert_utils-0.3.0.dist-info/METADATA
pytest_assert_utils-0.3.0.dist-info/RECORD
